futurecandy/__main__.py
futurecandy/candy.cfg
futurecandy/hooks/Git.py
futurecandy/hooks/Gitignore.py
futurecandy/hooks/Gitignore.py.gitignore
futurecandy/hooks/License.py
futurecandy/hooks/Safe.py
futurecandy/hooks/Venv.py
futurecandy/hooks/auto-gitignore-LICENSE
futurecandy-1.3.dist-info/LICENSE
futurecandy-1.3.dist-info/WHEEL
futurecandy-1.3.dist-info/METADATA
futurecandy-1.3.dist-info/RECORD
